openrouter_agent/__init__.py
openrouter_agent/agent.py
openrouter_agent/cli.py
openrouter_agent/config.py
openrouter_agent/example_bot.py
openrouter_agent-0.1.3.dist-info/METADATA
openrouter_agent-0.1.3.dist-info/WHEEL
openrouter_agent-0.1.3.dist-info/entry_points.txt
openrouter_agent-0.1.3.dist-info/RECORD
