Metadata-Version: 2.3
Name: openrouter-agent
Version: 0.1.3
Summary: This package provides integration between Pydantic AI and OpenRouter, allowing you to use any model available on OpenRouter with the Pydantic AI framework. The implementation leverages the OpenAI-compatible API provided by OpenRouter.
License: MIT
Author: VinnyVanGogh
Author-email: 133192356+VinnyVanGogh@users.noreply.github.com
Requires-Python: >=3.11,<4.0
Classifier: License :: OSI Approved :: MIT License
Classifier: Programming Language :: Python :: 3
Classifier: Programming Language :: Python :: 3.11
Classifier: Programming Language :: Python :: 3.12
Classifier: Programming Language :: Python :: 3.13
Requires-Dist: click (>=8.1.8,<9.0.0)
Requires-Dist: pydantic-ai (>=0.0.54,<0.0.55)
Requires-Dist: pyperclip (>=1.9.0,<2.0.0)
Requires-Dist: python-dotenv (>=1.1.0,<2.0.0)
Requires-Dist: rich (>=13.7.0,<14.0.0)
